pyisqc/__init__.py
pyisqc/_about.py
pyisqc/_caller.py
pyisqc/_compile.py
pyisqc/_downloader.py
pyisqc/_run.py
pyisqc/_simulate.py
pyisqc/utils.py
pyisqc-2.8.0.dist-info/LICENSE
pyisqc-2.8.0.dist-info/METADATA
pyisqc-2.8.0.dist-info/WHEEL
pyisqc-2.8.0.dist-info/top_level.txt
pyisqc-2.8.0.dist-info/RECORD
